{"header":"PROCESSED on Sat, 17 Feb 2024 08:53:04 +0000 from https:\/\/www.europeanyoga.org\/euyws\/euyws\/fr\/congres-zinal-2024\/","files":{"wp-polyfill-inert":{"url":"\/wp-includes\/js\/dist\/vendor\/wp-polyfill-inert.min.js","success":true},"regenerator-runtime":{"url":"\/wp-includes\/js\/dist\/vendor\/regenerator-runtime.min.js","success":true},"wp-polyfill":{"url":"\/wp-includes\/js\/dist\/vendor\/wp-polyfill.min.js","success":true},"wpcf7-recaptcha":{"url":"\/wp-content\/plugins\/contact-form-7\/modules\/recaptcha\/index.js","success":true},"happy-elementor-addons":{"url":"\/wp-content\/plugins\/happy-elementor-addons\/assets\/js\/happy-addons.min.js","success":true},"jquery-numerator":{"url":"\/wp-content\/plugins\/elementor\/assets\/lib\/jquery-numerator\/jquery-numerator.min.js","success":true},"font-awesome-4-shim":{"url":"\/wp-content\/plugins\/elementor\/assets\/lib\/font-awesome\/js\/v4-shims.min.js","success":true},"mc4wp-forms-api":{"url":"\/wp-content\/plugins\/mailchimp-for-wp\/assets\/js\/forms.js","success":true},"elementor-webpack-runtime":{"url":"\/wp-content\/plugins\/elementor\/assets\/js\/webpack.runtime.min.js","success":true},"elementor-frontend-modules":{"url":"\/wp-content\/plugins\/elementor\/assets\/js\/frontend-modules.min.js","success":true},"elementor-waypoints":{"url":"\/wp-content\/plugins\/elementor\/assets\/lib\/waypoints\/waypoints.min.js","success":true}}}